setup.cfg
setup.py
gctest/__init__.py
gctest/debug.py
gctest/test.py
gctest.egg-info/PKG-INFO
gctest.egg-info/SOURCES.txt
gctest.egg-info/dependency_links.txt
gctest.egg-info/entry_points.txt
gctest.egg-info/not-zip-safe
gctest.egg-info/requires.txt
gctest.egg-info/top_level.txt
gctest/tools/__init__.py
gctest/tools/common.py