Metadata-Version: 1.0
Name: gctest
Version: 1.0.0
Summary: Test Flask Sample
Home-page: UNKNOWN
Author: ChenJie
Author-email: chenjie@galachip.com
License: UNKNOWN
Platform: UNKNOWN
